{
  "knowledge discovery and data mining": "A",
  "acm sigkdd conference on knowledge discovery and data mining": "A",
  "very large data bases": "A",
  "international conference on machine learning": "A",
  "international conference on learning representations": "A",
  "advances in neural information processing systems": "A",
  "aaai conference on artificial intelligence": "A",
  "international joint conference on artificial intelligence": "A",
  "conference on computer vision and pattern recognition": "A",
  "international conference on software engineering": "A",
  "acm conference on computer and communications security": "A",
  "network and distributed system security symposium": "A"
}
